staticwordpress/__init__.py
staticwordpress/cli/__init__.py
staticwordpress/core/__init__.py
staticwordpress/core/constants.py
staticwordpress/core/crawler.py
staticwordpress/core/errors.py
staticwordpress/core/github.py
staticwordpress/core/i18n.py
staticwordpress/core/project.py
staticwordpress/core/redirects.py
staticwordpress/core/search.py
staticwordpress/core/sitemaps.py
staticwordpress/core/utils.py
staticwordpress/core/workflow.py
staticwordpress/gui/__init__.py
staticwordpress/gui/config.py
staticwordpress/gui/editor.py
staticwordpress/gui/logger.py
staticwordpress/gui/main.py
staticwordpress/gui/messagebox.py
staticwordpress/gui/project.py
staticwordpress/gui/rawtext.py
staticwordpress/gui/table.py
staticwordpress/gui/utils.py
staticwordpress/gui/workflow.py
staticwordpress/share/config.json
staticwordpress/share/gui.json
staticwordpress/share/robots.txt
staticwordpress/share/search.js
staticwordpress/share/translations.yaml
staticwordpress/share/icons/additionals.svg
staticwordpress/share/icons/bug-outline.svg
staticwordpress/share/icons/cancel.svg
staticwordpress/share/icons/check_project.svg
staticwordpress/share/icons/clear_all.svg
staticwordpress/share/icons/close-box-outline.svg
staticwordpress/share/icons/cloud-upload-outline.svg
staticwordpress/share/icons/configs.svg
staticwordpress/share/icons/content-save-outline.svg
staticwordpress/share/icons/crawl_website.svg
staticwordpress/share/icons/delete-outline.svg
staticwordpress/share/icons/delete-repo.svg
staticwordpress/share/icons/delete.svg
staticwordpress/share/icons/error.svg
staticwordpress/share/icons/exit-to-app.svg
staticwordpress/share/icons/file-document-remove-outline.svg
staticwordpress/share/icons/file-outline.svg
staticwordpress/share/icons/folder-git.svg
staticwordpress/share/icons/folder-off.svg
staticwordpress/share/icons/folder-outline.svg
staticwordpress/share/icons/github.svg
staticwordpress/share/icons/help-box-outline.svg
staticwordpress/share/icons/information-variant.svg
staticwordpress-0.0.7.dist-info/LICENSE
staticwordpress-0.0.7.dist-info/METADATA
staticwordpress-0.0.7.dist-info/WHEEL
staticwordpress-0.0.7.dist-info/entry_points.txt
staticwordpress-0.0.7.dist-info/top_level.txt
staticwordpress-0.0.7.dist-info/RECORD
