Metadata-Version: 2.1
Name: staticwordpress
Version: 0.0.7
Summary: Python Package for Converting WordPress Installation to a Static Website
Home-page: https://github.com/serpwings/static-wordpress
Download-URL: https://github.com/serpwings/static-wordpress/releases/v0.0.7.tar.gz
Author: Faisal Shahzad
Author-email: info@serpwings.com
License: GPLv3+
Keywords: wordpress,static-site-generators,search-engines,seo
Classifier: Development Status :: 1 - Planning
Classifier: Environment :: Console
Classifier: Environment :: X11 Applications
Classifier: Intended Audience :: Developers
Classifier: Intended Audience :: Education
Classifier: Intended Audience :: Information Technology
Classifier: Intended Audience :: Science/Research
Classifier: Intended Audience :: System Administrators
Classifier: License :: OSI Approved :: GNU General Public License v3 or later (GPLv3+)
Classifier: Operating System :: MacOS
Classifier: Operating System :: POSIX :: BSD
Classifier: Operating System :: POSIX :: Linux
Classifier: Programming Language :: Python :: 3
Classifier: Programming Language :: Python :: 3.8
Classifier: Programming Language :: Python :: 3.9
Classifier: Programming Language :: Python :: 3.10
Classifier: Programming Language :: Python :: 3.11
Classifier: Programming Language :: Python :: 3.12
Classifier: Programming Language :: Python :: 3 :: Only
Classifier: Programming Language :: Python :: Implementation :: CPython
Classifier: Topic :: Scientific/Engineering
Classifier: Topic :: System
Classifier: Topic :: System :: Archiving
Classifier: Topic :: System :: Archiving :: Backup
Classifier: Topic :: System :: Archiving :: Mirroring
Classifier: Topic :: System :: Filesystems
Classifier: Topic :: System :: Systems Administration
Classifier: Topic :: Utilities
Requires-Python: >=3.8
License-File: LICENSE
Requires-Dist: click
Requires-Dist: pyyaml
Requires-Dist: requests
Requires-Dist: beautifulsoup4
Requires-Dist: lxml
Requires-Dist: GitPython
Requires-Dist: PyGithub
Requires-Dist: PyYAML
Provides-Extra: dev
Requires-Dist: black; extra == "dev"
Requires-Dist: python-language-server[all]; extra == "dev"
Requires-Dist: setuptools; extra == "dev"
Requires-Dist: twine; extra == "dev"
Requires-Dist: wheel; extra == "dev"
Requires-Dist: setuptools; extra == "dev"
Requires-Dist: pytest; extra == "dev"
Requires-Dist: pytest-cov; extra == "dev"
Requires-Dist: twine; extra == "dev"
Requires-Dist: wheel; extra == "dev"
Requires-Dist: mkdocs; extra == "dev"
Requires-Dist: mkdocs-gen-files; extra == "dev"
Requires-Dist: mkdocstrings[python]; extra == "dev"
Requires-Dist: pymdown-extensions; extra == "dev"
Provides-Extra: gui
Requires-Dist: pyqt5; extra == "gui"
Requires-Dist: qtconsole; extra == "gui"
Provides-Extra: all
Requires-Dist: python-language-server[all]; extra == "all"
Requires-Dist: pytest-cov; extra == "all"
Requires-Dist: pyqt5; extra == "all"
Requires-Dist: pytest; extra == "all"
Requires-Dist: mkdocstrings[python]; extra == "all"
Requires-Dist: pymdown-extensions; extra == "all"
Requires-Dist: qtconsole; extra == "all"
Requires-Dist: twine; extra == "all"
Requires-Dist: mkdocs-gen-files; extra == "all"
Requires-Dist: mkdocs; extra == "all"
Requires-Dist: wheel; extra == "all"
Requires-Dist: black; extra == "all"
Requires-Dist: setuptools; extra == "all"
